ejtrader_iq/__init__.py
ejtrader_iq/api.py
ejtrader_iq/constants.py
ejtrader_iq/country_id.py
ejtrader_iq/expiration.py
ejtrader_iq/global_value.py
ejtrader_iq/stable_api.py
ejtrader_iq/http/__init__.py
ejtrader_iq/http/appinit.py
ejtrader_iq/http/auth.py
ejtrader_iq/http/billing.py
ejtrader_iq/http/buyback.py
ejtrader_iq/http/changebalance.py
ejtrader_iq/http/events.py
ejtrader_iq/http/getprofile.py
ejtrader_iq/http/getregdata.py
ejtrader_iq/http/login.py
ejtrader_iq/http/loginv2.py
ejtrader_iq/http/logout.py
ejtrader_iq/http/profile.py
ejtrader_iq/http/register.py
ejtrader_iq/http/resource.py
ejtrader_iq/http/token.py
ejtrader_iq/ws/__init__.py
ejtrader_iq/ws/client.py
ejtrader_iq/ws/chanels/__init__.py
ejtrader_iq/ws/chanels/api_game_betinfo.py
ejtrader_iq/ws/chanels/api_game_getoptions.py
ejtrader_iq/ws/chanels/base.py
ejtrader_iq/ws/chanels/buy_place_order_temp.py
ejtrader_iq/ws/chanels/buyback.py
ejtrader_iq/ws/chanels/buyv2.py
ejtrader_iq/ws/chanels/buyv3.py
ejtrader_iq/ws/chanels/cancel_order.py
ejtrader_iq/ws/chanels/candles.py
ejtrader_iq/ws/chanels/change_auto_margin_call.py
ejtrader_iq/ws/chanels/change_tpsl.py
ejtrader_iq/ws/chanels/changebalance.py
ejtrader_iq/ws/chanels/close_position.py
ejtrader_iq/ws/chanels/digital_option.py
ejtrader_iq/ws/chanels/get_available_leverages.py
ejtrader_iq/ws/chanels/get_balances.py
ejtrader_iq/ws/chanels/get_deferred_orders.py
ejtrader_iq/ws/chanels/get_financial_information.py
ejtrader_iq/ws/chanels/get_order.py
ejtrader_iq/ws/chanels/get_overnight_fee.py
ejtrader_iq/ws/chanels/get_positions.py
ejtrader_iq/ws/chanels/heartbeat.py
ejtrader_iq/ws/chanels/instruments.py
ejtrader_iq/ws/chanels/leaderboard.py
ejtrader_iq/ws/chanels/sell_option.py
ejtrader_iq/ws/chanels/setactives.py
ejtrader_iq/ws/chanels/ssid.py
ejtrader_iq/ws/chanels/strike_list.py
ejtrader_iq/ws/chanels/subscribe.py
ejtrader_iq/ws/chanels/traders_mood.py
ejtrader_iq/ws/chanels/unsubscribe.py
ejtrader_iq/ws/chanels/user.py
ejtrader_iq-0.0.1.dist-info/METADATA
ejtrader_iq-0.0.1.dist-info/WHEEL
ejtrader_iq-0.0.1.dist-info/top_level.txt
ejtrader_iq-0.0.1.dist-info/RECORD
