Metadata-Version: 2.1
Name: ejtrader-iq
Version: 0.0.1
Summary: IQ Option API for python
Home-page: https://github.com/traderpedroso/ejtrader_iq
Author: Emerson Pedroso
Author-email: emerson@ejtrader.com
License: UNKNOWN
Platform: UNKNOWN
Requires-Dist: pylint
Requires-Dist: requests
Requires-Dist: websocket-client (==0.56)
